lesty/__init__.py
lesty/cli.py
lesty-0.2.0.dist-info/LICENSE.txt
lesty-0.2.0.dist-info/METADATA
lesty-0.2.0.dist-info/WHEEL
lesty-0.2.0.dist-info/entry_points.txt
lesty-0.2.0.dist-info/top_level.txt
lesty-0.2.0.dist-info/RECORD
