Metadata-Version: 2.2
Name: lesty
Version: 0.2.0
Summary: A simple CLI tool to test lambdas using an event.json file
Author: José Schafer
Author-email: José Schafer <joseignacio.schafer@gmail.com>
License: MIT
Requires-Python: >=3.6
License-File: LICENSE.txt
Requires-Dist: python-dotenv>=1.0.1
Requires-Dist: typer>=0.9.4
Dynamic: author
Dynamic: requires-python
